src/aipp/__init__.py
src/aipp/builder.py
src/aipp/processors.py
src/aipp/processors/__init__.py
src/aipp/processors/base.py
src/aipp/processors/formatting.py
src/aipp/processors/reasoning.py
src/aipp/processors/role.py
src/aipp/processors/structured.py
aipp-0.1.3.dist-info/METADATA
aipp-0.1.3.dist-info/WHEEL
aipp-0.1.3.dist-info/licenses/LICENSE
aipp-0.1.3.dist-info/RECORD
