Metadata-Version: 2.4
Name: aipp
Version: 0.1.3
Summary: Generativ AI Prompt Processor
Project-URL: Homepage, https://github.com/descoped/aipp
Project-URL: Repository, https://github.com/descoped/aipp
Project-URL: Issues, https://github.com/descoped/aipp/issues
Author-email: Ove Ranheim <oranheim@gmail.com>
License-File: LICENSE
Keywords: ai,llm,processor,prompt
Classifier: License :: OSI Approved :: MIT License
Classifier: Operating System :: OS Independent
Classifier: Programming Language :: Python :: 3
Classifier: Programming Language :: Python :: 3.11
Classifier: Programming Language :: Python :: 3.12
Classifier: Programming Language :: Python :: 3.13
Requires-Python: >=3.11
